{"name":"Brahmavadin (IAPSOP)","type":"link","mylink":"http:\/\/iapsop.com\/archive\/materials\/brahmavadin","mytitle":"Brahmavadin (IAPSOP)","mylang":"de","content":"  Brahmavadin (IAPSOP)        About   Archives   Practices   Contribute   Contacts   Search\n\n &nbsp; &nbsp;     Periodical:  Brahmavadin<\/I>     \n\n      Summary:  From Pat Deveney's database:\n\n  Brahmavadin, The.\r\n A Monthly Religious and Philosophical Journal \/ The Monthly Magazine of Religion, Philosophy and Allied Subjects.\r\n That which exists is one: sages call it variously\r\n 1895--1914  Semimonthly, monthly (from 1898)\r\n Triplicane, Madras, India.\r\n Editor: Alasinga Perumal (1865-1909).\r\n Publisher: Tripilicant (Madras), Thompson & Co. (New York).  Succeeded by: Vedanta Kesari (1914-present)\r\n  1\/1, September 1895-19\/, March-April 1914.\r\n  Rs. 4\/ $2.00  a year.\n\n  This was published by Alasinga Perumal after Swami Vivekananda had suggested the project to  him and it was devoted to Vedanta as envisioned by Vivekananda  It contained contributions by various swamis who sought to spread the word of Vedanta to the West, such as Sister Nivedita and Swami Abhedananda,  but also contained occasional articles on Islam, Christianity, Jainism, etc.  Noted in The Metaphysical Magazine, 1896,  \"List of Advance Thought Publications,\" The New Cycle, March 1900, 159-60, and The Metaphysical Magazine, February 1901, 159, and in Notes and Queries, January 1900.    Issues:Brahmavadin V4 N1 - V4 NS 23-24 Oct 1898-Sep 1899     \r\n    <\/p>\n\n  \r\nIAPSOP materials are licensed under a Creative Commons Attribution-NonCommercial 4.0 International License. \r\n IAPSOP respects people's privacy and personal data rights.             <\/HTML>\n\n[1] http:\/\/iapsop.com\/archive\/materials\/brahmavadin","_id":736}